sockjsproxy
