Metadata-Version: 1.1
Name: sockjsproxy
Version: 0.7.1
Summary: SockJSProxy - Proxy SockJS messages to/from ZeroMQ PUSH/PULL sockets.
Home-page: https://bitbucket.org/vladev/sockjsproxy
Author: Emil Ivanov
Author-email: emil.vladev@gmail.com
License: MIT
Platform: UNKNOWN
Classifier: Development Status :: 4 - Beta
Classifier: Intended Audience :: Developers
Classifier: License :: OSI Approved :: MIT License
Classifier: Programming Language :: Python
Classifier: Topic :: Database
Classifier: Topic :: Software Development :: Libraries :: Python Modules
Classifier: Operating System :: Microsoft :: Windows
Classifier: Operating System :: Unix
